{
  "bots_version": "4.0.0",
  "plugins": {
    "channel": [
      {
        "plugintype": "channel",
        "apop": false,
        "archivepath": "",
        "askmdn": "",
        "certfile": "",
        "charset": "us-ascii",
        "desc": "",
        "filename": "*",
        "ftpaccount": "",
        "ftpactive": false,
        "ftpbinary": true,
        "host": "",
        "idchannel": "inbound_edifact_in",
        "inorout": "in",
        "keyfile": "",
        "lockname": "",
        "mdnchannel": "",
        "parameters": "",
        "path": "botssys/infile/demo_idoc/inbound_edifact",
        "port": 0,
        "remove": false,
        "rsrv1": null,
        "rsrv2": null,
        "rsrv3": null,
        "secret": "",
        "sendmdn": "",
        "starttls": false,
        "syslock": false,
        "testpath": "",
        "type": "file",
        "username": ""
      },
      {
        "plugintype": "channel",
        "apop": false,
        "archivepath": "",
        "askmdn": "",
        "certfile": "",
        "charset": "us-ascii",
        "desc": "",
        "filename": "*.idoc",
        "ftpaccount": "",
        "ftpactive": false,
        "ftpbinary": true,
        "host": "",
        "idchannel": "inbound_edifact_out",
        "inorout": "out",
        "keyfile": "",
        "lockname": "",
        "mdnchannel": "",
        "parameters": "",
        "path": "botssys/outfile/demo_idoc/idoc_orders",
        "port": 0,
        "remove": true,
        "rsrv1": null,
        "rsrv2": null,
        "rsrv3": null,
        "secret": "",
        "sendmdn": "",
        "starttls": false,
        "syslock": false,
        "testpath": "",
        "type": "file",
        "username": ""
      },
      {
        "plugintype": "channel",
        "apop": false,
        "archivepath": "",
        "askmdn": "",
        "certfile": "",
        "charset": "us-ascii",
        "desc": "",
        "filename": "*.idoc",
        "ftpaccount": "",
        "ftpactive": false,
        "ftpbinary": true,
        "host": "",
        "idchannel": "outbound_orders_in",
        "inorout": "in",
        "keyfile": "",
        "lockname": "",
        "mdnchannel": "",
        "parameters": "",
        "path": "botssys/infile/demo_idoc/1201ORDERS01",
        "port": 0,
        "remove": false,
        "rsrv1": null,
        "rsrv2": null,
        "rsrv3": null,
        "secret": "",
        "sendmdn": "",
        "starttls": false,
        "syslock": false,
        "testpath": "",
        "type": "file",
        "username": ""
      },
      {
        "plugintype": "channel",
        "apop": false,
        "archivepath": "",
        "askmdn": "",
        "certfile": "",
        "charset": "UNOC",
        "desc": "",
        "filename": "*.edi",
        "ftpaccount": "",
        "ftpactive": false,
        "ftpbinary": true,
        "host": "",
        "idchannel": "outbound_orders_out",
        "inorout": "out",
        "keyfile": "",
        "lockname": "",
        "mdnchannel": "",
        "parameters": "",
        "path": "botssys/outfile/demo_idoc/edifact_orders",
        "port": 0,
        "remove": true,
        "rsrv1": null,
        "rsrv2": null,
        "rsrv3": null,
        "secret": "",
        "sendmdn": "",
        "starttls": false,
        "syslock": false,
        "testpath": "",
        "type": "file",
        "username": ""
      },
      {
        "plugintype": "channel",
        "apop": false,
        "archivepath": "",
        "askmdn": "",
        "certfile": "",
        "charset": "us-ascii",
        "desc": "",
        "filename": "*.idoc",
        "ftpaccount": "",
        "ftpactive": false,
        "ftpbinary": true,
        "host": "",
        "idchannel": "outbound_pricat_in",
        "inorout": "in",
        "keyfile": "",
        "lockname": "",
        "mdnchannel": "",
        "parameters": "",
        "path": "botssys/infile/demo_idoc/1205WP_PLU02",
        "port": 0,
        "remove": false,
        "rsrv1": null,
        "rsrv2": null,
        "rsrv3": null,
        "secret": "",
        "sendmdn": "",
        "starttls": false,
        "syslock": false,
        "testpath": "",
        "type": "file",
        "username": ""
      },
      {
        "plugintype": "channel",
        "apop": false,
        "archivepath": "",
        "askmdn": "",
        "certfile": "",
        "charset": "UNOC",
        "desc": "",
        "filename": "*.edi",
        "ftpaccount": "",
        "ftpactive": false,
        "ftpbinary": true,
        "host": "",
        "idchannel": "outbound_pricat_out",
        "inorout": "out",
        "keyfile": "",
        "lockname": "",
        "mdnchannel": "",
        "parameters": "",
        "path": "botssys/outfile/demo_idoc/edifact_pricat",
        "port": 0,
        "remove": true,
        "rsrv1": null,
        "rsrv2": null,
        "rsrv3": null,
        "secret": "",
        "sendmdn": "",
        "starttls": false,
        "syslock": false,
        "testpath": "",
        "type": "file",
        "username": ""
      }
    ],
    "routes": [
      {
        "plugintype": "routes",
        "active": true,
        "alt": "",
        "defer": false,
        "desc": "",
        "fromchannel": "inbound_edifact_in",
        "fromeditype": "edifact",
        "frommessagetype": "edifact",
        "frompartner": null,
        "frompartner_tochannel": null,
        "idroute": "inbound_orders_edifact2idoc",
        "notindefaultrun": false,
        "rsrv1": null,
        "rsrv2": null,
        "seq": 9999,
        "testindicator": "",
        "tochannel": "inbound_edifact_out",
        "toeditype": "",
        "tomessagetype": "",
        "topartner": null,
        "topartner_tochannel": null,
        "translateind": 1,
        "zip_incoming": null,
        "zip_outgoing": null
      },
      {
        "plugintype": "routes",
        "active": true,
        "alt": "",
        "defer": false,
        "desc": "",
        "fromchannel": "outbound_orders_in",
        "fromeditype": "idoc",
        "frommessagetype": "ORDERS01",
        "frompartner": null,
        "frompartner_tochannel": null,
        "idroute": "outbound_orders_idoc2edifact",
        "notindefaultrun": false,
        "rsrv1": null,
        "rsrv2": null,
        "seq": 9999,
        "testindicator": "",
        "tochannel": "outbound_orders_out",
        "toeditype": "",
        "tomessagetype": "",
        "topartner": null,
        "topartner_tochannel": null,
        "translateind": 1,
        "zip_incoming": null,
        "zip_outgoing": null
      },
      {
        "plugintype": "routes",
        "active": true,
        "alt": "",
        "defer": false,
        "desc": "",
        "fromchannel": "outbound_pricat_in",
        "fromeditype": "idoc",
        "frommessagetype": "WP_PLU02",
        "frompartner": null,
        "frompartner_tochannel": null,
        "idroute": "outbound_pricat_idoc2edifact",
        "notindefaultrun": false,
        "rsrv1": null,
        "rsrv2": null,
        "seq": 9999,
        "testindicator": "",
        "tochannel": "outbound_pricat_out",
        "toeditype": "",
        "tomessagetype": "",
        "topartner": null,
        "topartner_tochannel": null,
        "translateind": 1,
        "zip_incoming": null,
        "zip_outgoing": null
      }
    ],
    "translate": [
      {
        "plugintype": "translate",
        "active": true,
        "alt": "",
        "desc": null,
        "fromeditype": "edifact",
        "frommessagetype": "ORDERSD96AUNEAN008",
        "frompartner": null,
        "rsrv1": null,
        "rsrv2": null,
        "toeditype": "idoc",
        "tomessagetype": "ORDERS01",
        "topartner": null,
        "tscript": "ORDERSD96A2ORDERS01"
      },
      {
        "plugintype": "translate",
        "active": true,
        "alt": "",
        "desc": null,
        "fromeditype": "edifact",
        "frommessagetype": "PRICATD96AUNEAN005",
        "frompartner": null,
        "rsrv1": null,
        "rsrv2": null,
        "toeditype": "idoc",
        "tomessagetype": "WP_PLU02",
        "topartner": null,
        "tscript": "PRICATD96A2WP_PLU02"
      },
      {
        "plugintype": "translate",
        "active": true,
        "alt": "",
        "desc": null,
        "fromeditype": "idoc",
        "frommessagetype": "ORDERS01",
        "frompartner": null,
        "rsrv1": null,
        "rsrv2": null,
        "toeditype": "edifact",
        "tomessagetype": "ORDERSD96AUNEAN008",
        "topartner": null,
        "tscript": "ORDERS012ORDERSD96A"
      },
      {
        "plugintype": "translate",
        "active": true,
        "alt": "",
        "desc": null,
        "fromeditype": "idoc",
        "frommessagetype": "WP_PLU02",
        "frompartner": null,
        "rsrv1": null,
        "rsrv2": null,
        "toeditype": "edifact",
        "tomessagetype": "PRICATD96AUNEAN005",
        "topartner": null,
        "tscript": "WP_PLU022PRICATD96A"
      }
    ]
  }
}